fridgeyocr/__init__.py
fridgeyocr/detection.py
fridgeyocr/fridgeyocr.py
fridgeyocr/recognition.py
fridgeyocr/setup.py
fridgeyocr/config/__init__.py
fridgeyocr/pretrained_models/__init__.py
fridgeyocr/text_detection/__init__.py
fridgeyocr/text_detection/ctpn.py
fridgeyocr/text_detection/ctpn_anchor.py
fridgeyocr/text_detection/ctpn_connector.py
fridgeyocr/text_detection/ctpn_functions.py
fridgeyocr/text_detection/detection_utils.py
fridgeyocr/text_recognition/HENNET.py
fridgeyocr/text_recognition/__init__.py
fridgeyocr/text_recognition/attention.py
fridgeyocr/text_recognition/decoder.py
fridgeyocr/text_recognition/encoder.py
fridgeyocr/text_recognition/hennet_label_converter.py
fridgeyocr/text_recognition/mha_formula.py
fridgeyocr/text_recognition/position.py
fridgeyocr/text_recognition/resnet.py
fridgeyocr/text_recognition/transformer.py
fridgeyocr/text_recognition/jamo_utils/__init__.py
fridgeyocr/text_recognition/jamo_utils/jamo_merge.py
fridgeyocr/text_recognition/jamo_utils/jamo_split.py
fridgeyocr-0.1.5.dist-info/METADATA
fridgeyocr-0.1.5.dist-info/WHEEL
fridgeyocr-0.1.5.dist-info/top_level.txt
fridgeyocr-0.1.5.dist-info/RECORD
